{
  "lastUpdated": "2025-07-27T00:00:39.258Z",
  "stats": {
    "users": {
      "count": 52015,
      "change": 5.3
    },
    "revenue": {
      "amount": 249216,
      "change": 3.7
    },
    "projects": {
      "count": 364,
      "change": 4.4
    },
    "tasks": {
      "count": 2495,
      "change": 11.6
    }
  },
  "activities": [
    {
      "type": "message",
      "title": "Invoice generated",
      "timestamp": "2025-07-27T00:00:39.258Z"
    },
    {
      "type": "payment",
      "title": "Invoice generated",
      "timestamp": "2025-07-26T00:00:28.844Z"
    },
    {
      "type": "user",
      "title": "Task completed",
      "timestamp": "2025-07-25T00:00:26.059Z"
    },
    {
      "type": "payment",
      "title": "System alert",
      "timestamp": "2025-07-24T00:01:02.972Z"
    },
    {
      "type": "message",
      "title": "New message",
      "timestamp": "2025-07-23T00:00:47.158Z"
    }
  ],
  "weeklyActivity": [
    {
      "day": "Mon",
      "value": 14
    },
    {
      "day": "Tue",
      "value": 18
    },
    {
      "day": "Wed",
      "value": 26
    },
    {
      "day": "Thu",
      "value": 10
    },
    {
      "day": "Fri",
      "value": 19
    },
    {
      "day": "Sat",
      "value": 72
    },
    {
      "day": "Sun",
      "value": 10
    }
  ],
  "performanceMetrics": [
    {
      "date": "2023-10-17",
      "value": 18
    },
    {
      "date": "2023-10-18",
      "value": 45
    },
    {
      "date": "2023-10-19",
      "value": 22
    },
    {
      "date": "2023-10-20",
      "value": 45
    },
    {
      "date": "2023-10-21",
      "value": 39
    },
    {
      "date": "2023-10-22",
      "value": 30
    },
    {
      "date": "2023-10-23",
      "value": 36
    }
  ]
}