{
  "lastUpdated": "2025-07-29T00:00:21.334Z",
  "stats": {
    "users": {
      "count": 54975,
      "change": 7.9
    },
    "revenue": {
      "amount": 252665,
      "change": 4.7
    },
    "projects": {
      "count": 365,
      "change": -1.7
    },
    "tasks": {
      "count": 2496,
      "change": 10.5
    }
  },
  "activities": [
    {
      "type": "message",
      "title": "New user registered",
      "timestamp": "2025-07-29T00:00:21.334Z"
    },
    {
      "type": "project",
      "title": "System alert",
      "timestamp": "2025-07-28T00:00:42.996Z"
    },
    {
      "type": "message",
      "title": "Invoice generated",
      "timestamp": "2025-07-27T00:00:39.258Z"
    },
    {
      "type": "payment",
      "title": "Invoice generated",
      "timestamp": "2025-07-26T00:00:28.844Z"
    },
    {
      "type": "user",
      "title": "Task completed",
      "timestamp": "2025-07-25T00:00:26.059Z"
    }
  ],
  "weeklyActivity": [
    {
      "day": "Mon",
      "value": 10
    },
    {
      "day": "Tue",
      "value": 23
    },
    {
      "day": "Wed",
      "value": 18
    },
    {
      "day": "Thu",
      "value": 19
    },
    {
      "day": "Fri",
      "value": 18
    },
    {
      "day": "Sat",
      "value": 89
    },
    {
      "day": "Sun",
      "value": 10
    }
  ],
  "performanceMetrics": [
    {
      "date": "2023-10-19",
      "value": 22
    },
    {
      "date": "2023-10-20",
      "value": 45
    },
    {
      "date": "2023-10-21",
      "value": 39
    },
    {
      "date": "2023-10-22",
      "value": 30
    },
    {
      "date": "2023-10-23",
      "value": 36
    },
    {
      "date": "2023-10-24",
      "value": 26
    },
    {
      "date": "2023-10-25",
      "value": 16
    }
  ]
}